{
  "status": "REAL",
  "source": "OpenAlex works API, fixed-seed random sample (keyless, CC0)",
  "sample_url": "https://api.openalex.org/works?sample=50&seed=42&per-page=50&select=id,display_name,cited_by_count,referenced_works_count,publication_year,primary_topic",
  "frozen_at": "2026-07-23",
  "note": "Real 50-work random sample fetched by the user from a browser (OpenAlex is network-blocked from the analysis session but keyless). Fields transcribed verbatim from the API 'results'. cited_by_count = forward citations; referenced_works_count = reference-list length; field = primary_topic.field.display_name (null if none).",
  "results": [
    {"id": "W585439491", "cited_by_count": 0, "referenced_works_count": 0, "publication_year": 2001, "field": "Engineering"},
    {"id": "W4245800925", "cited_by_count": 0, "referenced_works_count": 1, "publication_year": 2017, "field": "Medicine"},
    {"id": "W3006246480", "cited_by_count": 0, "referenced_works_count": 0, "publication_year": 2013, "field": "Health Professions"},
    {"id": "W7156196317", "cited_by_count": 0, "referenced_works_count": 0, "publication_year": 2026, "field": null},
    {"id": "W2738078980", "cited_by_count": 0, "referenced_works_count": 0, "publication_year": 2015, "field": "Engineering"},
    {"id": "W2414087141", "cited_by_count": 0, "referenced_works_count": 0, "publication_year": 1953, "field": "Arts and Humanities"},
    {"id": "W4391167565", "cited_by_count": 1, "referenced_works_count": 13, "publication_year": 2024, "field": "Medicine"},
    {"id": "W2848021", "cited_by_count": 0, "referenced_works_count": 0, "publication_year": 1997, "field": "Biochemistry, Genetics and Molecular Biology"},
    {"id": "W2413649893", "cited_by_count": 4, "referenced_works_count": 0, "publication_year": 1991, "field": "Environmental Science"},
    {"id": "W3176043942", "cited_by_count": 0, "referenced_works_count": 0, "publication_year": 2013, "field": "Engineering"},
    {"id": "W7169926711", "cited_by_count": 0, "referenced_works_count": 0, "publication_year": 2008, "field": null},
    {"id": "W4243247610", "cited_by_count": 0, "referenced_works_count": 0, "publication_year": 2016, "field": null},
    {"id": "W2119335518", "cited_by_count": 4, "referenced_works_count": 3, "publication_year": 2010, "field": "Engineering"},
    {"id": "W2602871348", "cited_by_count": 0, "referenced_works_count": 0, "publication_year": 2016, "field": "Engineering"},
    {"id": "W566972287", "cited_by_count": 0, "referenced_works_count": 0, "publication_year": 2015, "field": "Engineering"},
    {"id": "W2105662556", "cited_by_count": 11, "referenced_works_count": 12, "publication_year": 2007, "field": "Medicine"},
    {"id": "W2013472039", "cited_by_count": 99, "referenced_works_count": 44, "publication_year": 2014, "field": "Engineering"},
    {"id": "W2246825379", "cited_by_count": 0, "referenced_works_count": 0, "publication_year": 2000, "field": "Economics, Econometrics and Finance"},
    {"id": "W4397719545", "cited_by_count": 0, "referenced_works_count": 0, "publication_year": 2008, "field": "Materials Science"},
    {"id": "W4243771256", "cited_by_count": 0, "referenced_works_count": 0, "publication_year": 2020, "field": "Social Sciences"},
    {"id": "W4220663160", "cited_by_count": 1, "referenced_works_count": 0, "publication_year": 2022, "field": "Agricultural and Biological Sciences"},
    {"id": "W2373718252", "cited_by_count": 0, "referenced_works_count": 0, "publication_year": 2007, "field": "Computer Science"},
    {"id": "W2760359882", "cited_by_count": 1, "referenced_works_count": 0, "publication_year": 2001, "field": "Chemistry"},
    {"id": "W2760392869", "cited_by_count": 4, "referenced_works_count": 11, "publication_year": 2017, "field": "Medicine"},
    {"id": "W1995832530", "cited_by_count": 0, "referenced_works_count": 0, "publication_year": 1997, "field": "Nursing"},
    {"id": "W1974184976", "cited_by_count": 3, "referenced_works_count": 8, "publication_year": 2009, "field": "Mathematics"},
    {"id": "W3111851814", "cited_by_count": 0, "referenced_works_count": 0, "publication_year": 2020, "field": "Medicine"},
    {"id": "W7165117397", "cited_by_count": 0, "referenced_works_count": 30, "publication_year": 2026, "field": "Environmental Science"},
    {"id": "W2414143566", "cited_by_count": 0, "referenced_works_count": 0, "publication_year": 1957, "field": "Medicine"},
    {"id": "W3037746556", "cited_by_count": 16, "referenced_works_count": 51, "publication_year": 2020, "field": "Business, Management and Accounting"},
    {"id": "W2946645679", "cited_by_count": 0, "referenced_works_count": 0, "publication_year": 2010, "field": "Nursing"},
    {"id": "W2602577171", "cited_by_count": 0, "referenced_works_count": 0, "publication_year": 2016, "field": "Computer Science"},
    {"id": "W3093311002", "cited_by_count": 0, "referenced_works_count": 0, "publication_year": 1924, "field": "Physics and Astronomy"},
    {"id": "W2791760613", "cited_by_count": 0, "referenced_works_count": 0, "publication_year": 2017, "field": "Social Sciences"},
    {"id": "W1021479909", "cited_by_count": 0, "referenced_works_count": 0, "publication_year": 2001, "field": "Engineering"},
    {"id": "W4384852954", "cited_by_count": 0, "referenced_works_count": 0, "publication_year": 2023, "field": null},
    {"id": "W4307067669", "cited_by_count": 0, "referenced_works_count": 0, "publication_year": 2022, "field": "Environmental Science"},
    {"id": "W2886990492", "cited_by_count": 0, "referenced_works_count": 0, "publication_year": 2017, "field": "Social Sciences"},
    {"id": "W7105096371", "cited_by_count": 0, "referenced_works_count": 0, "publication_year": 2025, "field": null},
    {"id": "W4206652578", "cited_by_count": 10, "referenced_works_count": 0, "publication_year": 2014, "field": "Social Sciences"},
    {"id": "W2101409125", "cited_by_count": 0, "referenced_works_count": 0, "publication_year": 2013, "field": "Medicine"},
    {"id": "W4405800125", "cited_by_count": 2, "referenced_works_count": 49, "publication_year": 2024, "field": "Materials Science"},
    {"id": "W7149577059", "cited_by_count": 0, "referenced_works_count": 0, "publication_year": 2026, "field": null},
    {"id": "W2322863670", "cited_by_count": 1, "referenced_works_count": 0, "publication_year": 1970, "field": "Social Sciences"},
    {"id": "W2415930734", "cited_by_count": 0, "referenced_works_count": 0, "publication_year": 2005, "field": "Medicine"},
    {"id": "W4387700918", "cited_by_count": 3, "referenced_works_count": 42, "publication_year": 2023, "field": "Materials Science"},
    {"id": "W3009572898", "cited_by_count": 4, "referenced_works_count": 34, "publication_year": 2020, "field": "Computer Science"},
    {"id": "W4391045369", "cited_by_count": 0, "referenced_works_count": 0, "publication_year": 2024, "field": null},
    {"id": "W2759112353", "cited_by_count": 2, "referenced_works_count": 0, "publication_year": 1879, "field": "Agricultural and Biological Sciences"},
    {"id": "W4385176873", "cited_by_count": 0, "referenced_works_count": 0, "publication_year": 2022, "field": null}
  ]
}
